memvid_mcp_server/__about__.py
memvid_mcp_server/__init__.py
memvid_mcp_server/docker_lifecycle.py
memvid_mcp_server/main.py
iflow_mcp_angrysky56_memvid_mcp_server-0.2.1.dist-info/METADATA
iflow_mcp_angrysky56_memvid_mcp_server-0.2.1.dist-info/WHEEL
iflow_mcp_angrysky56_memvid_mcp_server-0.2.1.dist-info/entry_points.txt
iflow_mcp_angrysky56_memvid_mcp_server-0.2.1.dist-info/RECORD
