Metadata-Version: 2.4
Name: iflow-mcp_angrysky56_memvid_mcp_server
Version: 0.2.1
Summary: An MCP server to expose Memvid functionalities to AI clients
Project-URL: Repository, https://github.com/angrysky56/memvid_mcp_server
Project-URL: Issues, https://github.com/angrysky56/memvid_mcp_server/issues
Author: AI Workspace
License-Expression: MIT
Keywords: ai,mcp,memory,memvid,video
Classifier: Development Status :: 4 - Beta
Classifier: Programming Language :: Python
Classifier: Programming Language :: Python :: 3.10
Classifier: Programming Language :: Python :: 3.11
Classifier: Programming Language :: Python :: 3.12
Requires-Python: >=3.10
Requires-Dist: anthropic>=0.57.1
Requires-Dist: faiss-cpu>=1.11.0
Requires-Dist: google-genai>=1.24.0
Requires-Dist: google-generativeai>=0.8.5
Requires-Dist: mcp[cli]>=1.10.1
Requires-Dist: memvid
Requires-Dist: openai>=1.93.0
Requires-Dist: pypdf2
Provides-Extra: dev
Requires-Dist: black>=23.0.0; extra == 'dev'
Requires-Dist: mypy>=1.0.0; extra == 'dev'
Requires-Dist: pytest-asyncio>=0.21.0; extra == 'dev'
Requires-Dist: pytest>=7.0.0; extra == 'dev'
Requires-Dist: ruff>=0.1.0; extra == 'dev'
Provides-Extra: gpu
Requires-Dist: faiss-gpu-cu12>=1.11.0; extra == 'gpu'
